<?xml version="1.0" encoding="utf-8"?>
<Entity parent="template_unit_mechanical_ship_galley_3">
  <Identity>
    <Civ>athen</Civ>
    <Icon>units/hele_ship_trireme.png</Icon>
    <GenericName>Athenian Trireme</GenericName>
    <SpecificName>Triḗrēs Athēnaía</SpecificName>
  </Identity>
  <ProductionQueue>
    <BatchTimeModifier>0.7</BatchTimeModifier>
    <Entities datatype="tokens">
      units/athen_champion_sword_infantry
      units/athen_mercenary_javelin_infantry
      units/athen_mercenary_archer_infantry
      units/athen_mercenary_sling_infantry
    </Entities>
    <TechCostMultiplier>
      <food>1.0</food>
      <wood>1.0</wood>
      <stone>1.0</stone>
      <metal>1.0</metal>
      <time>1.0</time>
    </TechCostMultiplier>
  </ProductionQueue>
  <VisualActor>
    <Actor>structures/athenians/trireme.xml</Actor>
  </VisualActor>
</Entity>
