<?xml version="1.0" encoding="utf-8"?>
<Entity parent="template_unit_cavalry_melee">
  <Armour>
    <Hack op="add">4</Hack>
    <Pierce op="add">4</Pierce>
  </Armour>
  <Attack>
    <Melee>
      <Bonuses>
        <Skirmisher>
          <Classes>Cavalry Javelin</Classes>
          <Multiplier>1.5</Multiplier>
        </Skirmisher>
      </Bonuses>      
      <Crush>2</Crush>
      <Pierce>8</Pierce>
      <PreferredClasses datatype="tokens">Skirmisher</PreferredClasses>
      <PrepareTime>800</PrepareTime>
    </Melee>
  </Attack>
  <Cost>
    <Resources>
      <metal op="add">30</metal>
      <wood op="add">20</wood>
    </Resources>
  </Cost>
  <Health>
    <Max op="mul">1.7</Max>
  </Health>
  <Identity>
    <GenericName>Cavalry Lancer</GenericName>
    <Tooltip>Counters: 1.5× vs Cavalry Javelinists.
Penalties: 0.75× vs Camels, Chariots, 0.5× vs Elephants.</Tooltip>
    <VisibleClasses datatype="tokens">Cataphract</VisibleClasses>
  </Identity>
  <Loot>
    <metal op="add">3</metal>
    <wood op="add">2</wood>
    <xp op="add">50</xp>
  </Loot>
  <UnitMotion>
    <Run>
      <Range>700.0</Range>
      <RangeMin>10.0</RangeMin>
      <Speed>40.0</Speed>
    </Run>
    <WalkSpeed>20.0</WalkSpeed>
  </UnitMotion>
</Entity>
