<?xml version="1.0" encoding="utf-8"?>
<Entity parent="template_unit_infantry_melee">
  <Attack>
    <Melee>
      <Hack>1.2</Hack>
      <MaxRange op="mul">2.0</MaxRange>
      <Pierce>4.8</Pierce>
    </Melee>
  </Attack>
  <Cost>
    <Resources>
      <metal op="add">25</metal>
      <wood op="add">25</wood>
    </Resources>
  </Cost>
  <Health>
    <Max op="mul">2.0</Max>
  </Health>
  <Identity>
    <GenericName>Hoplite</GenericName>
    <VisibleClasses datatype="tokens">Hoplite</VisibleClasses>
  </Identity>
  <UnitMotion>
    <WalkSpeed op="mul">0.7</WalkSpeed>
  </UnitMotion>
</Entity>
